raga_llm_eval/__init__.py
raga_llm_eval/api_client_manager.py
raga_llm_eval/db_manager.py
raga_llm_eval/raga_llm_eval.py
raga_llm_eval/raga_llm_observer.py
raga_llm_eval/result_manager.py
raga_llm_eval/test_manager.py
raga_llm_eval/track_manager.py
raga_llm_eval/guardrails/__init__.py
raga_llm_eval/guardrails/anonymize.py
raga_llm_eval/guardrails/ban_competitors.py
raga_llm_eval/guardrails/ban_substrings.py
raga_llm_eval/guardrails/ban_topics.py
raga_llm_eval/guardrails/code.py
raga_llm_eval/guardrails/deanonymize.py
raga_llm_eval/guardrails/factual_consistency.py
raga_llm_eval/guardrails/gibberish.py
raga_llm_eval/guardrails/invisible_text.py
raga_llm_eval/guardrails/ir_metrics_test.py
raga_llm_eval/guardrails/json_verify.py
raga_llm_eval/guardrails/language.py
raga_llm_eval/guardrails/language_same.py
raga_llm_eval/guardrails/malicious_url.py
raga_llm_eval/guardrails/match_type.py
raga_llm_eval/guardrails/no_refusal.py
raga_llm_eval/guardrails/nsfw.py
raga_llm_eval/guardrails/politeness.py
raga_llm_eval/guardrails/profanity.py
raga_llm_eval/guardrails/reading_time.py
raga_llm_eval/guardrails/regex.py
raga_llm_eval/guardrails/secrets.py
raga_llm_eval/guardrails/sensitive.py
raga_llm_eval/guardrails/sentiment.py
raga_llm_eval/guardrails/token_limit.py
raga_llm_eval/guardrails/url_reachability.py
raga_llm_eval/guardrails/utils.py
raga_llm_eval/guardrails/valid_csv.py
raga_llm_eval/guardrails/valid_python.py
raga_llm_eval/guardrails/valid_sql.py
raga_llm_eval/guardrails/vault.py
raga_llm_eval/guardrails/anonymize_helpers/__init__.py
raga_llm_eval/guardrails/anonymize_helpers/analyzer.py
raga_llm_eval/guardrails/anonymize_helpers/exception.py
raga_llm_eval/guardrails/anonymize_helpers/faker.py
raga_llm_eval/guardrails/anonymize_helpers/ner_mapping.py
raga_llm_eval/guardrails/anonymize_helpers/regex_patterns.py
raga_llm_eval/guardrails/anonymize_helpers/transformers_helpers.py
raga_llm_eval/guardrails/anonymize_helpers/transformers_recognizer.py
raga_llm_eval-2.1.0.dist-info/LICENSE
raga_llm_eval-2.1.0.dist-info/METADATA
raga_llm_eval-2.1.0.dist-info/WHEEL
raga_llm_eval-2.1.0.dist-info/entry_points.txt
raga_llm_eval-2.1.0.dist-info/top_level.txt
raga_llm_eval-2.1.0.dist-info/RECORD
